README.rst
setup.py
wa/__init__.py
wa/api.py
wa/cli.py
wa/env.py
wa/utils.py
wa/version.py
wa.egg-info/PKG-INFO
wa.egg-info/SOURCES.txt
wa.egg-info/dependency_links.txt
wa.egg-info/entry_points.txt
wa.egg-info/requires.txt
wa.egg-info/top_level.txt