Metadata-Version: 1.1
Name: wa
Version: 0.1.0
Summary: Workflow automation tool
Home-page: https://github.com/char16t/wa
Author: Valeriy Manenkov
Author-email: v.manenkov@gmail.com
License: MIT
Download-URL: https://github.com/char16t/wa/archive/master.tar.gz
Platform: UNKNOWN
Classifier: Environment :: Console
Classifier: License :: OSI Approved :: MIT License
Classifier: Development Status :: 3 - Alpha
Classifier: Intended Audience :: Developers
Classifier: Operating System :: OS Independent
Classifier: Programming Language :: Python
Classifier: Programming Language :: Python :: 3
